diceparse.py
pydiceparse-0.5.1.4.dist-info/METADATA
pydiceparse-0.5.1.4.dist-info/WHEEL
pydiceparse-0.5.1.4.dist-info/entry_points.txt
pydiceparse-0.5.1.4.dist-info/top_level.txt
pydiceparse-0.5.1.4.dist-info/RECORD
