Metadata-Version: 2.1
Name: pydiceparse
Version: 0.5.1.4
Summary: Dice syntax parser and roller
Home-page: https://github.com/tritium21/pydiceparse
Author: Alex Walters
Author-email: tritium@sdamon.com
License: BSD
Platform: UNKNOWN
Classifier: Development Status :: 4 - Beta
Classifier: Environment :: Console
Classifier: Intended Audience :: Developers
Classifier: Intended Audience :: End Users/Desktop
Classifier: License :: OSI Approved :: BSD License
Classifier: Natural Language :: English
Classifier: Programming Language :: Python :: 2
Classifier: Programming Language :: Python :: 3
Requires-Dist: lark-parser (>=0.6.3)
